[
  {
    "Name": "Mario",
    "IconFile": "/Assets/mp4/Characters/Mario.png"
  },
  {
    "Name": "Luigi",
    "IconFile": "/Assets/mp4/Characters/Luigi.png"
  },
  {
    "Name": "Peach",
    "IconFile": "/Assets/mp4/Characters/Peach.png"
  },
  {
    "Name": "Yoshi",
    "IconFile": "/Assets/mp4/Characters/Yoshi.png"
  },
  {
    "Name": "Wario",
    "IconFile": "/Assets/mp4/Characters/Wario.png"
  },
  {
    "Name": "Donkey Kong",
    "IconFile": "/Assets/mp4/Characters/DK.png"
  },
  {
    "Name": "Daisy",
    "IconFile": "/Assets/mp4/Characters/Daisy.png"
  },
  {
    "Name": "Waluigi",
    "IconFile": "/Assets/mp4/Characters/Waluigi.png"
  }
]